playground/__init__.py
playground/playground.py
rust_playground-0.1.1.dist-info/METADATA
rust_playground-0.1.1.dist-info/RECORD
rust_playground-0.1.1.dist-info/WHEEL
rust_playground-0.1.1.dist-info/entry_points.txt
rust_playground-0.1.1.dist-info/top_level.txt
