Metadata-Version: 2.1
Name: rust-playground
Version: 0.1.1
Summary: Use Python to execute simple Rust code by running it on https://play.rust-lang.org/
Home-page: https://www.github.com/ritiek/rust-without-rust
Author: Ritiek Malhotra
Author-email: ritiekmalhotra123@gmail.com
License: MIT
Download-URL: https://github.com/ritiek/rust-without-rust/archive/v0.1.1.tar.gz
Keywords: rust,python,playground
Platform: UNKNOWN
